[{"id":1,"first_name":"Lenna","last_name":"Stonall","email":"lstonall0@1688.com","age":77},
{"id":2,"first_name":"Kalindi","last_name":"Aindrais","email":"kaindrais1@icio.us","age":56},
{"id":3,"first_name":"Quinn","last_name":"Parriss","email":"qparriss2@auda.org.au","age":68},
{"id":4,"first_name":"Wrennie","last_name":"Howison","email":"whowison3@google.nl","age":24},
{"id":5,"first_name":"Dexter","last_name":"Critten","email":"dcritten4@pbs.org","age":49},
{"id":6,"first_name":"Granger","last_name":"Cicculini","email":"gcicculini5@arizona.edu","age":24},
// {"id":7,"first_name":"Dulcie","last_name":"Spurrior","email":"dspurrior6@posterous.com","age":79},
// {"id":8,"first_name":"Burgess","last_name":"Darwent","email":"bdarwent7@sciencedirect.com","age":43},
// {"id":9,"first_name":"Lamar","last_name":"MacCroary","email":"lmaccroary8@icio.us","age":32},
// {"id":10,"first_name":"Fransisco","last_name":"Burley","email":"fburley9@mlb.com","age":20},
// {"id":11,"first_name":"Keir","last_name":"Brunroth","email":"kbrunrotha@mozilla.org","age":24},
// {"id":12,"first_name":"Babbie","last_name":"Weerdenburg","email":"bweerdenburgb@merriam-webster.com","age":40},
// {"id":13,"first_name":"Cherise","last_name":"Morales","email":"cmoralesc@cmu.edu","age":22},
// {"id":14,"first_name":"Margarete","last_name":"Newlove","email":"mnewloved@wikipedia.org","age":22},
// {"id":15,"first_name":"Gaynor","last_name":"Jager","email":"gjagere@nbcnews.com","age":45},
// {"id":16,"first_name":"Taffy","last_name":"Hoggan","email":"thogganf@vimeo.com","age":75},
// {"id":17,"first_name":"Silvan","last_name":"Bellany","email":"sbellanyg@businesswire.com","age":79},
// {"id":18,"first_name":"Jamie","last_name":"Brandreth","email":"jbrandrethh@alexa.com","age":79},
// {"id":19,"first_name":"Corene","last_name":"Best","email":"cbesti@techcrunch.com","age":46},
// {"id":20,"first_name":"Casi","last_name":"Landsborough","email":"clandsboroughj@networksolutions.com","age":71},
// {"id":21,"first_name":"Elliot","last_name":"Skase","email":"eskasek@redcross.org","age":56},
// {"id":22,"first_name":"Willyt","last_name":"Rospars","email":"wrosparsl@state.gov","age":74},
// {"id":23,"first_name":"Tawnya","last_name":"Sleightholm","email":"tsleightholmm@symantec.com","age":64},
// {"id":24,"first_name":"Jillie","last_name":"Turfin","email":"jturfinn@tripod.com","age":68},
// {"id":25,"first_name":"Carlota","last_name":"Timoney","email":"ctimoneyo@xing.com","age":34}
]